{"boundaries":[{"feature_ids":["feat:origin.assurance-entity-origin-field","feat:origin.assurance-entity-origin-validation","feat:origin.assurance-origin-cli-flags","feat:origin.repo-local-assurance-rows","feat:origin.downstream-ssot-core-row-ban","feat:origin.downstream-ssot-origin-row-sync"],"frozen":true,"id":"bnd:origin-scoped-assurance-entities.v1","profile_ids":["prf:origin-scoped-assurance-entities"],"status":"frozen","title":"Origin-scoped assurance entities v1"}],"boundary":{"feature_ids":["feat:origin.assurance-entity-origin-field","feat:origin.assurance-entity-origin-validation","feat:origin.assurance-origin-cli-flags","feat:origin.repo-local-assurance-rows","feat:origin.downstream-ssot-core-row-ban","feat:origin.downstream-ssot-origin-row-sync"],"frozen":true,"id":"bnd:origin-scoped-assurance-entities.v1","profile_ids":["prf:origin-scoped-assurance-entities"],"status":"frozen","title":"Origin-scoped assurance entities v1"},"claims":[{"description":"Planned conformance claim for feat:origin.assurance-entity-origin-field before boundary certification.","evidence_ids":["evd:planned.origin.assurance-entity-origin-field.report"],"feature_ids":["feat:origin.assurance-entity-origin-field"],"id":"clm:planned.origin.assurance-entity-origin-field.t1","kind":"conformance","origin":"ssot-core","status":"promoted","test_ids":["tst:planned.origin.assurance-entity-origin-field"],"tier":"T1","title":"Planned claim for Assurance entity origin field"},{"description":"Planned conformance claim for feat:origin.assurance-entity-origin-validation before boundary certification.","evidence_ids":["evd:planned.origin.assurance-entity-origin-validation.report"],"feature_ids":["feat:origin.assurance-entity-origin-validation"],"id":"clm:planned.origin.assurance-entity-origin-validation.t1","kind":"conformance","origin":"ssot-core","status":"promoted","test_ids":["tst:planned.origin.assurance-entity-origin-validation"],"tier":"T1","title":"Planned claim for Assurance entity origin validation"},{"description":"Planned conformance claim for feat:origin.assurance-origin-cli-flags before boundary certification.","evidence_ids":["evd:planned.origin.assurance-origin-cli-flags.report"],"feature_ids":["feat:origin.assurance-origin-cli-flags"],"id":"clm:planned.origin.assurance-origin-cli-flags.t2","kind":"conformance","origin":"ssot-core","status":"promoted","test_ids":["tst:planned.origin.assurance-origin-cli-flags"],"tier":"T2","title":"Planned claim for Assurance origin CLI flags"},{"description":"Planned conformance claim for feat:origin.repo-local-assurance-rows before boundary certification.","evidence_ids":["evd:planned.origin.repo-local-assurance-rows.report"],"feature_ids":["feat:origin.repo-local-assurance-rows"],"id":"clm:planned.origin.repo-local-assurance-rows.t1","kind":"conformance","origin":"ssot-core","status":"promoted","test_ids":["tst:planned.origin.repo-local-assurance-rows"],"tier":"T1","title":"Planned claim for Repo-local assurance rows"},{"description":"Planned conformance claim for feat:origin.downstream-ssot-core-row-ban before boundary certification.","evidence_ids":["evd:planned.origin.downstream-ssot-core-row-ban.report"],"feature_ids":["feat:origin.downstream-ssot-core-row-ban"],"id":"clm:planned.origin.downstream-ssot-core-row-ban.t1","kind":"conformance","origin":"ssot-core","status":"promoted","test_ids":["tst:planned.origin.downstream-ssot-core-row-ban"],"tier":"T1","title":"Planned claim for Downstream ssot-core assurance row ban"},{"description":"Planned conformance claim for feat:origin.downstream-ssot-origin-row-sync before boundary certification.","evidence_ids":["evd:planned.origin.downstream-ssot-origin-row-sync.report"],"feature_ids":["feat:origin.downstream-ssot-origin-row-sync"],"id":"clm:planned.origin.downstream-ssot-origin-row-sync.t1","kind":"conformance","origin":"ssot-core","status":"promoted","test_ids":["tst:planned.origin.downstream-ssot-origin-row-sync"],"tier":"T1","title":"Planned claim for Downstream ssot-origin assurance row sync"}],"evidence":[{"claim_ids":["clm:planned.origin.assurance-entity-origin-field.t1"],"id":"evd:planned.origin.assurance-entity-origin-field.report","kind":"report","origin":"ssot-core","path":".ssot/evidence/reports/assurance-origin-model.json","status":"passed","test_ids":["tst:planned.origin.assurance-entity-origin-field"],"tier":"T1","title":"Planned evidence for Assurance entity origin field"},{"claim_ids":["clm:planned.origin.assurance-entity-origin-validation.t1"],"id":"evd:planned.origin.assurance-entity-origin-validation.report","kind":"report","origin":"ssot-core","path":".ssot/evidence/reports/assurance-origin-model.json","status":"passed","test_ids":["tst:planned.origin.assurance-entity-origin-validation"],"tier":"T1","title":"Planned evidence for Assurance entity origin validation"},{"claim_ids":["clm:planned.origin.assurance-origin-cli-flags.t2"],"id":"evd:planned.origin.assurance-origin-cli-flags.report","kind":"report","origin":"ssot-core","path":".ssot/evidence/reports/assurance-origin-model.json","robustness_dimensions":["cross_surface","negative_cases"],"source_evidence_ids":["evd:planned.origin.assurance-entity-origin-field.report","evd:planned.origin.assurance-entity-origin-validation.report"],"status":"passed","test_ids":["tst:planned.origin.assurance-origin-cli-flags"],"tier":"T2","title":"Planned evidence for Assurance origin CLI flags"},{"claim_ids":["clm:planned.origin.downstream-ssot-core-row-ban.t1"],"id":"evd:planned.origin.downstream-ssot-core-row-ban.report","kind":"report","origin":"ssot-core","path":".ssot/evidence/reports/assurance-origin-model.json","status":"passed","test_ids":["tst:planned.origin.downstream-ssot-core-row-ban"],"tier":"T1","title":"Planned evidence for Downstream ssot-core assurance row ban"},{"claim_ids":["clm:planned.origin.downstream-ssot-origin-row-sync.t1"],"id":"evd:planned.origin.downstream-ssot-origin-row-sync.report","kind":"report","origin":"ssot-core","path":".ssot/evidence/reports/assurance-origin-model.json","status":"passed","test_ids":["tst:planned.origin.downstream-ssot-origin-row-sync"],"tier":"T1","title":"Planned evidence for Downstream ssot-origin assurance row sync"},{"claim_ids":["clm:planned.origin.repo-local-assurance-rows.t1"],"id":"evd:planned.origin.repo-local-assurance-rows.report","kind":"report","origin":"ssot-core","path":".ssot/evidence/reports/assurance-origin-model.json","status":"passed","test_ids":["tst:planned.origin.repo-local-assurance-rows"],"tier":"T1","title":"Planned evidence for Repo-local assurance rows"}],"features":[{"claim_ids":["clm:planned.origin.assurance-entity-origin-field.t1"],"description":"Add origin ownership metadata to feature, test, claim, and evidence rows.","id":"feat:origin.assurance-entity-origin-field","implementation_status":"implemented","lifecycle":{"note":null,"replacement_feature_ids":[],"stage":"active"},"origin":"ssot-core","plan":{"horizon":"explicit","slot":"rel:origin-scoped-assurance-entities.v1","target_claim_tier":"T1","target_lifecycle_stage":"active"},"requires":[],"spec_ids":["spc:0533"],"test_ids":["tst:planned.origin.assurance-entity-origin-field"],"title":"Assurance entity origin field"},{"claim_ids":["clm:planned.origin.assurance-entity-origin-validation.t1"],"description":"Validate allowed origin values and ownership transitions for assurance entity rows.","id":"feat:origin.assurance-entity-origin-validation","implementation_status":"implemented","lifecycle":{"note":null,"replacement_feature_ids":[],"stage":"active"},"origin":"ssot-core","plan":{"horizon":"explicit","slot":"rel:origin-scoped-assurance-entities.v1","target_claim_tier":"T1","target_lifecycle_stage":"active"},"requires":[],"spec_ids":["spc:0533"],"test_ids":["tst:planned.origin.assurance-entity-origin-validation"],"title":"Assurance entity origin validation"},{"claim_ids":["clm:planned.origin.assurance-origin-cli-flags.t2"],"description":"Expose origin selection and filtering on feature, test, claim, and evidence CLI surfaces where supported.","id":"feat:origin.assurance-origin-cli-flags","implementation_status":"implemented","lifecycle":{"note":null,"replacement_feature_ids":[],"stage":"active"},"origin":"ssot-core","plan":{"horizon":"explicit","slot":"rel:origin-scoped-assurance-entities.v1","target_claim_tier":"T2","target_lifecycle_stage":"active"},"requires":[],"spec_ids":["spc:0533"],"test_ids":["tst:planned.origin.assurance-origin-cli-flags"],"title":"Assurance origin CLI flags"},{"claim_ids":["clm:planned.origin.downstream-ssot-core-row-ban.t1"],"description":"Prevent downstream repo-local repositories from creating or mutating ssot-core feature, test, claim, or evidence rows.","id":"feat:origin.downstream-ssot-core-row-ban","implementation_status":"implemented","lifecycle":{"note":null,"replacement_feature_ids":[],"stage":"active"},"origin":"ssot-core","plan":{"horizon":"explicit","slot":"rel:origin-scoped-assurance-entities.v1","target_claim_tier":"T1","target_lifecycle_stage":"active"},"requires":[],"spec_ids":["spc:0533"],"test_ids":["tst:planned.origin.downstream-ssot-core-row-ban"],"title":"Downstream ssot-core assurance row ban"},{"claim_ids":["clm:planned.origin.downstream-ssot-origin-row-sync.t1"],"description":"Allow downstream repositories to synchronize ssot-origin assurance rows as governed shared compliance obligations.","id":"feat:origin.downstream-ssot-origin-row-sync","implementation_status":"implemented","lifecycle":{"note":null,"replacement_feature_ids":[],"stage":"active"},"origin":"ssot-core","plan":{"horizon":"explicit","slot":"rel:origin-scoped-assurance-entities.v1","target_claim_tier":"T1","target_lifecycle_stage":"active"},"requires":[],"spec_ids":["spc:0533"],"test_ids":["tst:planned.origin.downstream-ssot-origin-row-sync"],"title":"Downstream ssot-origin assurance row sync"},{"claim_ids":["clm:planned.origin.repo-local-assurance-rows.t1"],"description":"Define locally authored feature, test, claim, and evidence rows as repo-local assurance rows.","id":"feat:origin.repo-local-assurance-rows","implementation_status":"implemented","lifecycle":{"note":null,"replacement_feature_ids":[],"stage":"active"},"origin":"ssot-core","plan":{"horizon":"explicit","slot":"rel:origin-scoped-assurance-entities.v1","target_claim_tier":"T1","target_lifecycle_stage":"active"},"requires":[],"spec_ids":["spc:0533"],"test_ids":["tst:planned.origin.repo-local-assurance-rows"],"title":"Repo-local assurance rows"}],"file_hashes":{".ssot/evidence/reports/assurance-origin-model.json":"d0d2691363e2be26834403add3ba8364592b5a24d3224bb055f0279501d13772","tests/integration/test_cli_assurance_origin.py":"e7688be3adaaa25a93457f093d1ac984f681d85cde493e71eb4cc1d1d5b6c627","tests/unit/test_assurance_origin_model.py":"81113377ea55f5bbabdf4af03d79e7cdfa951b5e1f0cb4e180d1246aec91980d"},"generated_at":"2026-05-17T00:57:38Z","kind":"release_snapshot","profile_evaluations":[{"checks":{"all_features_passing":true,"has_features":true},"failures":[],"feature_results":[{"checked_claim_ids":["clm:planned.origin.assurance-entity-origin-field.t1"],"checks":{"claim_target_met":true,"implemented":true,"required_features_passing":true},"failures":[],"feature_id":"feat:origin.assurance-entity-origin-field","passed":true,"required_tier":"T1","satisfying_claim_ids":["clm:planned.origin.assurance-entity-origin-field.t1"]},{"checked_claim_ids":["clm:planned.origin.assurance-entity-origin-validation.t1"],"checks":{"claim_target_met":true,"implemented":true,"required_features_passing":true},"failures":[],"feature_id":"feat:origin.assurance-entity-origin-validation","passed":true,"required_tier":"T1","satisfying_claim_ids":["clm:planned.origin.assurance-entity-origin-validation.t1"]},{"checked_claim_ids":["clm:planned.origin.downstream-ssot-core-row-ban.t1"],"checks":{"claim_target_met":true,"implemented":true,"required_features_passing":true},"failures":[],"feature_id":"feat:origin.downstream-ssot-core-row-ban","passed":true,"required_tier":"T1","satisfying_claim_ids":["clm:planned.origin.downstream-ssot-core-row-ban.t1"]},{"checked_claim_ids":["clm:planned.origin.downstream-ssot-origin-row-sync.t1"],"checks":{"claim_target_met":true,"implemented":true,"required_features_passing":true},"failures":[],"feature_id":"feat:origin.downstream-ssot-origin-row-sync","passed":true,"required_tier":"T1","satisfying_claim_ids":["clm:planned.origin.downstream-ssot-origin-row-sync.t1"]},{"checked_claim_ids":["clm:planned.origin.repo-local-assurance-rows.t1"],"checks":{"claim_target_met":true,"implemented":true,"required_features_passing":true},"failures":[],"feature_id":"feat:origin.repo-local-assurance-rows","passed":true,"required_tier":"T1","satisfying_claim_ids":["clm:planned.origin.repo-local-assurance-rows.t1"]},{"checked_claim_ids":["clm:planned.origin.assurance-origin-cli-flags.t2"],"checks":{"claim_target_met":true,"implemented":true,"required_features_passing":true},"failures":[],"feature_id":"feat:origin.assurance-origin-cli-flags","passed":true,"required_tier":"T2","satisfying_claim_ids":["clm:planned.origin.assurance-origin-cli-flags.t2"]}],"passed":true,"profile_id":"prf:origin-scoped-assurance-entities","resolved_feature_ids":["feat:origin.assurance-entity-origin-field","feat:origin.assurance-entity-origin-validation","feat:origin.downstream-ssot-core-row-ban","feat:origin.downstream-ssot-origin-row-sync","feat:origin.repo-local-assurance-rows","feat:origin.assurance-origin-cli-flags"]}],"profiles":[{"claim_tier":"T2","description":"Reusable profile for distinguishing ssot-core, ssot-origin, and repo-local assurance rows across features, tests, claims, and evidence.","evaluation":{"allow_feature_override_tier":true,"mode":"all_features_must_pass"},"feature_ids":["feat:origin.assurance-entity-origin-field","feat:origin.assurance-entity-origin-validation","feat:origin.downstream-ssot-core-row-ban","feat:origin.downstream-ssot-origin-row-sync","feat:origin.repo-local-assurance-rows","feat:origin.assurance-origin-cli-flags"],"id":"prf:origin-scoped-assurance-entities","kind":"certification","profile_ids":[],"status":"draft","title":"Origin-scoped assurance entities"}],"registry_path":".ssot/registry.json","registry_sha256":"0ca08692252c41f8f045bd99a9bd832b15faed46ff2e8b9620c002c147afb13d","release":{"body":null,"boundary_id":"bnd:origin-scoped-assurance-entities.v1","boundary_ids":["bnd:origin-scoped-assurance-entities.v1"],"claim_ids":["clm:planned.origin.assurance-entity-origin-field.t1","clm:planned.origin.assurance-entity-origin-validation.t1","clm:planned.origin.assurance-origin-cli-flags.t2","clm:planned.origin.repo-local-assurance-rows.t1","clm:planned.origin.downstream-ssot-core-row-ban.t1","clm:planned.origin.downstream-ssot-origin-row-sync.t1"],"evidence_ids":["evd:planned.origin.assurance-entity-origin-field.report","evd:planned.origin.assurance-entity-origin-validation.report","evd:planned.origin.assurance-origin-cli-flags.report","evd:planned.origin.repo-local-assurance-rows.report","evd:planned.origin.downstream-ssot-core-row-ban.report","evd:planned.origin.downstream-ssot-origin-row-sync.report"],"id":"rel:origin-scoped-assurance-entities.v1","status":"promoted","version":"origin-scoped-assurance-entities.v1"},"schema_version":1,"summary":{"boundary_count":1,"boundary_id":"bnd:origin-scoped-assurance-entities.v1","boundary_ids":["bnd:origin-scoped-assurance-entities.v1"],"claim_count":6,"evidence_count":6,"feature_count":6,"profile_count":1,"release_id":"rel:origin-scoped-assurance-entities.v1","status":"promoted","test_count":6,"version":"origin-scoped-assurance-entities.v1"},"tests":[{"claim_ids":["clm:planned.origin.assurance-entity-origin-field.t1"],"evidence_ids":["evd:planned.origin.assurance-entity-origin-field.report"],"execution":{"argv":["uv","run","pytest","tests/unit/test_assurance_origin_model.py","-q"],"cwd":".","env":{"UV_CACHE_DIR":".uv-cache"},"mode":"command","success":{"expected":0,"type":"exit_code"},"timeout_seconds":600},"feature_ids":["feat:origin.assurance-entity-origin-field"],"id":"tst:planned.origin.assurance-entity-origin-field","kind":"pytest","origin":"ssot-core","path":"tests/unit/test_assurance_origin_model.py","status":"passing","title":"Planned test for Assurance entity origin field"},{"claim_ids":["clm:planned.origin.assurance-entity-origin-validation.t1"],"evidence_ids":["evd:planned.origin.assurance-entity-origin-validation.report"],"execution":{"argv":["uv","run","pytest","tests/unit/test_assurance_origin_model.py","-q"],"cwd":".","env":{"UV_CACHE_DIR":".uv-cache"},"mode":"command","success":{"expected":0,"type":"exit_code"},"timeout_seconds":600},"feature_ids":["feat:origin.assurance-entity-origin-validation"],"id":"tst:planned.origin.assurance-entity-origin-validation","kind":"pytest","origin":"ssot-core","path":"tests/unit/test_assurance_origin_model.py","status":"passing","title":"Planned test for Assurance entity origin validation"},{"claim_ids":["clm:planned.origin.assurance-origin-cli-flags.t2"],"evidence_ids":["evd:planned.origin.assurance-origin-cli-flags.report"],"execution":{"argv":["uv","run","pytest","tests/integration/test_cli_assurance_origin.py","-q"],"cwd":".","env":{"UV_CACHE_DIR":".uv-cache"},"mode":"command","success":{"expected":0,"type":"exit_code"},"timeout_seconds":600},"feature_ids":["feat:origin.assurance-origin-cli-flags"],"id":"tst:planned.origin.assurance-origin-cli-flags","kind":"pytest","origin":"ssot-core","path":"tests/integration/test_cli_assurance_origin.py","status":"passing","title":"Planned test for Assurance origin CLI flags"},{"claim_ids":["clm:planned.origin.downstream-ssot-core-row-ban.t1"],"evidence_ids":["evd:planned.origin.downstream-ssot-core-row-ban.report"],"execution":{"argv":["uv","run","pytest","tests/unit/test_assurance_origin_model.py","tests/integration/test_cli_assurance_origin.py","-q"],"cwd":".","env":{"UV_CACHE_DIR":".uv-cache"},"mode":"command","success":{"expected":0,"type":"exit_code"},"timeout_seconds":600},"feature_ids":["feat:origin.downstream-ssot-core-row-ban"],"id":"tst:planned.origin.downstream-ssot-core-row-ban","kind":"pytest","origin":"ssot-core","path":"tests/unit/test_assurance_origin_model.py","status":"passing","title":"Planned test for Downstream ssot-core assurance row ban"},{"claim_ids":["clm:planned.origin.downstream-ssot-origin-row-sync.t1"],"evidence_ids":["evd:planned.origin.downstream-ssot-origin-row-sync.report"],"execution":{"argv":["uv","run","pytest","tests/unit/test_assurance_origin_model.py","-q"],"cwd":".","env":{"UV_CACHE_DIR":".uv-cache"},"mode":"command","success":{"expected":0,"type":"exit_code"},"timeout_seconds":600},"feature_ids":["feat:origin.downstream-ssot-origin-row-sync"],"id":"tst:planned.origin.downstream-ssot-origin-row-sync","kind":"pytest","origin":"ssot-core","path":"tests/unit/test_assurance_origin_model.py","status":"passing","title":"Planned test for Downstream ssot-origin assurance row sync"},{"claim_ids":["clm:planned.origin.repo-local-assurance-rows.t1"],"evidence_ids":["evd:planned.origin.repo-local-assurance-rows.report"],"execution":{"argv":["uv","run","pytest","tests/unit/test_assurance_origin_model.py","-q"],"cwd":".","env":{"UV_CACHE_DIR":".uv-cache"},"mode":"command","success":{"expected":0,"type":"exit_code"},"timeout_seconds":600},"feature_ids":["feat:origin.repo-local-assurance-rows"],"id":"tst:planned.origin.repo-local-assurance-rows","kind":"pytest","origin":"ssot-core","path":"tests/unit/test_assurance_origin_model.py","status":"passing","title":"Planned test for Repo-local assurance rows"}]}