{"boundary":{"feature_ids":["feat:registry.automated-status-sync"],"frozen":true,"id":"bnd:registry.automated-status-sync.v1","profile_ids":[],"status":"frozen","title":"Automated status sync v1 boundary"},"features":[{"claim_ids":["clm:registry.automated-status-sync.t1"],"description":"Derive and persist profile, feature, test, claim, and evidence statuses from registry proof chains.","id":"feat:registry.automated-status-sync","implementation_status":"implemented","lifecycle":{"note":null,"replacement_feature_ids":[],"stage":"active"},"plan":{"horizon":"current","slot":null,"target_claim_tier":"T1","target_lifecycle_stage":"active"},"requires":[],"spec_ids":["spc:0522"],"test_ids":["tst:registry.automated-status-sync.integration"],"title":"Automated registry status synchronization"}],"generated_at":"2026-04-22T06:14:37Z","kind":"boundary_snapshot","registry_path":".ssot/registry.json","registry_sha256":"fda2045d6ae9b066be70977bcfaa3146850f6332bf929e21801a9776a53bd9c9","schema_version":1,"summary":{"boundary_id":"bnd:registry.automated-status-sync.v1","feature_count":1,"frozen":true,"profile_count":0,"status":"frozen"}}